berag/__init__.py
berag/embedding.py
berag/pipeline.py
berag/retriever.py
berag/utils.py
berag-0.1.0.dist-info/METADATA
berag-0.1.0.dist-info/WHEEL
berag-0.1.0.dist-info/top_level.txt
berag-0.1.0.dist-info/RECORD
