Metadata-Version: 2.4
Name: berag
Version: 0.1.0
Summary: A modular RAG pipeline library for your own data
Home-page: https://github.com/your_github_username/berag
Author: Besanty Ezekiel
Classifier: Programming Language :: Python :: 3
Classifier: License :: OSI Approved :: MIT License
Requires-Python: >=3.8
Requires-Dist: openai
Requires-Dist: chromadb
Requires-Dist: sentence-transformers
Requires-Dist: langchain
Requires-Dist: tqdm
Requires-Dist: PyYAML
Requires-Dist: pypdf
Dynamic: author
Dynamic: classifier
Dynamic: description
Dynamic: description-content-type
Dynamic: home-page
Dynamic: requires-dist
Dynamic: requires-python
Dynamic: summary
